pyAmberElectric/__init__.py
pyAmberElectric/aws_srp.py
pyAmberElectric-0.0.2.dist-info/LICENSE
pyAmberElectric-0.0.2.dist-info/METADATA
pyAmberElectric-0.0.2.dist-info/WHEEL
pyAmberElectric-0.0.2.dist-info/top_level.txt
pyAmberElectric-0.0.2.dist-info/RECORD
