Metadata-Version: 2.1
Name: pyAmberElectric
Version: 0.0.2
Summary: Unofficial API for Amber Electric
Home-page: https://github.com/Bootlessjam/pyAmberElectric
Author: Todd Iancar
Author-email: bootlessjam@gmail.com
License: UNKNOWN
Project-URL: Bug Tracker, https://github.com/Bootlessjam/pyAmberElectric/issues
Platform: UNKNOWN
Classifier: Programming Language :: Python :: 3
Classifier: License :: OSI Approved :: Apache Software License
Classifier: Operating System :: OS Independent
Requires-Python: >=3.6
License-File: LICENSE
Requires-Dist: boto3
